Workbook
Name Tax_Rate: '06_DEFINED_NAMES'!$B$19
Name Report_Date: '06_DEFINED_NAMES'!$B$20
Name Target_Margin: '06_DEFINED_NAMES'!$B$21
Name Sales_Data: '06_DEFINED_NAMES'!$A$24:$F$29
Name Review_Threshold: 0.80
Name FD_Review_Target: '19_FULL_DISCOVERY'!$Q$26

Sheet 00_START_HERE
A1: Excel Workbook & Data Discovery — Practice Workbook
A3: Purpose: practice how to inspect an unfamiliar Excel workbook before cleaning, calculating, or analyzing it. Each EXERCISE sheet gives you a scenario, concrete questions, and space to answer. No solutions are included in this file.
A6: Recommended order
A7: 01_DATA_STRUCTURE | B7: Grain, identifiers, measures, dimensions
A8: 02_WORKBOOK_MAP | B8: Understand the role of multiple worksheets
A9: 03_TABLES_RANGES | B9: Recognize Excel Tables vs ordinary ranges
A10: 04_RELATIONSHIPS | B10: Identify keys and one-to-many relationships
A11: 05_RAW_DERIVED | B11: Distinguish source fields from calculated fields
A12: 06_DEFINED_NAMES | B12: Inspect Name Box / Name Manager objects
A13: 07_FORMULA_LOGIC | B13: Understand existing formula logic and dependencies
A14: 08_HIDDEN_DEP | B14: Find a hidden dependency used by formulas
A15: 09_PIVOT_READING | B15: Read Pivot logic and know what to inspect in a real PivotTable
A16: 10_EXTERNAL_CLUES | B16: Recognize external / query / connection clues safely
A17: 11_BUSINESS_TO_DATA | B17: Translate business questions into data requirements
A18: 12_AMBIGUITY | B18: Identify missing information and ambiguous requests
... A25: 19_FULL_DISCOVERY | B25: Combine discovery, quality, key, visibility, dependency, and validation skills
A27: How to use this workbook
A28: 1. Do the exercises in order. Do not search for an answer key — there is none in this file.
A29: 2. For each exercise, inspect the workbook using Excel itself. Write your reasoning in the blue answer cells.
A30: 3. Do not modify source data unless the task explicitly tells you to. Discovery is about understanding first.
A31: 4. When you finish an exercise, share the workbook or your answers for review before moving to the next one.
A32: 5. Later modules will go deeper into cleaning, formulas, lookups, aggregation, PivotTables, Power Query, visualization, and business analysis.
A35: Color convention: blue answer cells = your input; green text = source/imported data; black text = formulas/derived; orange = caution/review; purple = logic/control.
A38: Support sheets 02A–02C belong to Exercise 02. Hidden sheets are intentional discovery objects for Exercises 08 and 19; Exercise 15 contains hidden/filter state on the exercise sheet itself. Exercise 09 is a portable PivotTable-reading simulation, and Exercise 10 uses portable connection evidence rather than a live external source. Exercise 17 uses portable workbook-health clues rather than intentionally embedding broken formulas or changing global calculation settings.

Sheet 01_DATA_STRUCTURE
A1: Exercise 01 — Data Structure
A2: Capability | B2: Grain, Identifier, Measures, Dimensions
A3: Difficulty | B3: Foundation
A5: Scenario | B5: You receive a single transaction table. Do not calculate anything yet. Your job is to understand what the dataset represents before choosing any Excel function.
A8: Your task
A9: 1. What does one row represent (the grain)? | E9: Type your answer here
A10: 2. Which field is the strongest row-level identifier? | E10: Type your answer here
A11: 3. Which measures already exist in the table? | E11: Type your answer here
A12: 4. Which dimensions could be used to group or filter the data? | E12: Type your answer here
A13: 5. For the question “Which product generated the highest revenue?”, which fields are required, and is a new metric needed? | E13: Type your answer here
A16: Transaction_ID | B16: Date | C16: Customer_ID | D16: Product | E16: Category | F16: Region | G16: Units | H16: Unit_Price
A17: T001 | B17: 46204 | C17: C101 | D17: Laptop Pro | E17: Computers | F17: North | G17: 1 | H17: 1200
A18: T002 | B18: 46204 | C18: C102 | D18: Mouse X | E18: Accessories | F18: South | G18: 3 | H18: 30
A19: T003 | B19: 46205 | C19: C101 | D19: Keyboard K | E19: Accessories | F19: North | G19: 2 | H19: 75
A20: T004 | B20: 46205 | C20: C103 | D20: Laptop Air | E20: Computers | F20: West | G20: 1 | H20: 950
A21: T005 | B21: 46206 | C21: C104 | D21: Mouse X | E21: Accessories | F21: South | G21: 4 | H21: 30

Sheet 02_WORKBOOK_MAP
A1: Exercise 02 — Workbook Map
A2: Capability | B2: Understand workbook structure and worksheet roles
A3: Difficulty | B3: Foundation
A5: Scenario | B5: This workbook contains three support sheets for this exercise: 02A_SALES_RAW, 02B_PRODUCTS_REF, and 02C_REPORT_OUTPUT. Inspect all three before answering. Do not assume a sheet role only from its name.
A8: Your task
A9: 1. What is the likely role of each of the three support sheets? | E9: Type your answer here
A10: 2. Which sheet appears to contain source-level transactional data? | E10: Type your answer here
A11: 3. Which sheet appears to be a reference / lookup table, and what entity does one row represent there? | E11: Type your answer here
A12: 4. Which sheet contains derived output rather than raw source data? What evidence supports that conclusion? | E12: Type your answer here
A13: 5. If you were asked to add a new analysis, which sheet(s) would you avoid modifying first, and why? | E13: Type your answer here
A16: Tip: inspect formulas in the output sheet and compare them with the source sheets. The point is not to calculate — it is to map the workbook.

Sheet 02A_SALES_RAW
A1: Order_ID | B1: Date | C1: Customer_ID | D1: Product_ID | E1: Region | F1: Units | G1: Revenue
A2: O1001 | B2: 46174 | C2: C101 | D2: P01 | E2: North | F2: 1 | G2: 1200
A3: O1002 | B3: 46174 | C3: C102 | D3: P03 | E3: South | F3: 3 | G3: 90
A4: O1003 | B4: 46175 | C4: C103 | D4: P02 | E4: West | F4: 1 | G4: 950
A5: O1004 | B5: 46176 | C5: C101 | D5: P04 | E5: North | F5: 2 | G5: 150
A6: O1005 | B6: 46177 | C6: C104 | D6: P03 | E6: South | F6: 4 | G6: 120
A7: O1006 | B7: 46178 | C7: C105 | D7: P01 | E7: East | F7: 1 | G7: 1200

Sheet 02B_PRODUCTS_REF
A1: Product_ID | B1: Product | C1: Category | D1: Standard_Price
A2: P01 | B2: Laptop Pro | C2: Computers | D2: 1200
A3: P02 | B3: Laptop Air | C3: Computers | D3: 950
A4: P03 | B4: Mouse X | C4: Accessories | D4: 30
A5: P04 | B5: Keyboard K | C5: Accessories | D5: 75

Sheet 02C_REPORT_OUTPUT
A1: Sales Report
A4: KPI | B4: Value
A5: Total Revenue | B5: =SUM('02A_SALES_RAW'!G2:G7)
A6: North Revenue | B6: =SUMIF('02A_SALES_RAW'!E2:E7,"North",'02A_SALES_RAW'!G2:G7)
A7: Order Count | B7: =COUNTA('02A_SALES_RAW'!A2:A7)
A10: This sheet is intentionally output-oriented. Inspect formulas rather than treating displayed values as raw data.

Sheet 03_TABLES_RANGES
A1: Exercise 03 — Tables vs Ranges
A2: Capability | B2: Identify Excel Tables, table names, and ordinary ranges
A3: Difficulty | B3: Foundation
A5: Scenario | B5: Two data blocks are shown below. One is a real Excel Table and the other is an ordinary cell range. Use Excel itself to determine which is which and what that implies.
A8: Your task
A9: 1. Which data block is an Excel Table and which is an ordinary range? | E9: Type your answer here
A10: 2. What is the Excel Table name? | E10: Type your answer here
A11: 3. What clues in the Excel interface prove that the object is a Table? | E11: Type your answer here
A12: 4. If a new row is added directly below each block, which object is designed to expand automatically? | E12: Type your answer here
A13: 5. Why can Table names and structured ranges matter when auditing an unfamiliar workbook? | E13: Type your answer here
A16: Sale_ID | B16: Date | C16: Region | D16: Units | E16: Revenue | H16: Product_ID | I16: Product | J16: Category
A17: S01 | B17: 46143 | C17: North | D17: 2 | E17: 500 | H17: P01 | I17: Laptop Pro | J17: Computers
A18: S02 | B18: 46143 | C18: South | D18: 1 | E18: 300 | H18: P02 | I18: Laptop Air | J18: Computers
A19: S03 | B19: 46144 | C19: West | D19: 3 | E19: 750 | H19: P03 | I19: Mouse X | J19: Accessories
A20: S04 | B20: 46145 | C20: North | D20: 1 | E20: 250 | H20: P04 | I20: Keyboard K | J20: Accessories
A21: S05 | B21: 46146 | C21: East | D21: 4 | E21: 1000

Sheet 04_RELATIONSHIPS
A1: Exercise 04 — Keys & Relationships
A2: Capability | B2: Identify join keys and one-to-many relationships
A3: Difficulty | B3: Intermediate
A5: Scenario | B5: You receive three datasets on the same sheet. Do not perform any lookup yet. First determine how the datasets relate and where uniqueness should exist.
A8: Your task
A9: 1. What does one row represent in Sales, Products, and Customers? | E9: Type your answer here
A10: 2. Which field should connect Sales to Products? | E10: Type your answer here
A11: 3. Which field should connect Sales to Customers? | E11: Type your answer here
A12: 4. On which side of each relationship should the key be unique? | E12: Type your answer here
A13: 5. Would Order_ID alone be a safe row-level key in Sales? Explain from the data shown. | E13: Type your answer here
A16: Line_ID | B16: Order_ID | C16: Customer_ID | D16: Product_ID | E16: Date | F16: Units | G16: Revenue | I16: Product_ID | J16: Product | K16: Category | L16: Standard_Price | N16: Customer_ID | O16: Customer_Name | P16: Segment
A17: L001 | B17: O1001 | C17: C101 | D17: P01 | E17: 46204 | F17: 1 | G17: 1200 | I17: P01 | J17: Laptop Pro | K17: Computers | L17: 1200 | N17: C101 | O17: Orion Labs | P17: SMB
A18: L002 | B18: O1001 | C18: C101 | D18: P03 | E18: 46204 | F18: 2 | G18: 60 | I18: P02 | J18: Laptop Air | K18: Computers | L18: 950 | N18: C102 | O18: Nova Retail | P18: Enterprise
A19: L003 | B19: O1002 | C19: C102 | D19: P02 | E19: 46205 | F19: 1 | G19: 950 | I19: P03 | J19: Mouse X | K19: Accessories | L19: 30 | N19: C103 | O19: Blue Peak | P19: SMB
A20: L004 | B20: O1003 | C20: C103 | D20: P03 | E20: 46205 | F20: 4 | G20: 120 | I20: P04 | J20: Keyboard K | K20: Accessories | L20: 75
A21: L005 | B21: O1004 | C21: C101 | D21: P04 | E21: 46206 | F21: 1 | G21: 75

Sheet 05_RAW_DERIVED
A1: Exercise 05 — Raw vs Derived
A2: Capability | B2: Distinguish source values from calculated fields and spot formula patterns
A3: Difficulty | B3: Intermediate
A5: Scenario | B5: An analyst has already worked on this table. Some columns are source inputs and others are calculated inside Excel. Inspect formulas before deciding what each field means.
A8: Your task
A9: 1. Which columns appear to be source fields and which are derived/calculated? | E9: Type your answer here
A10: 2. What is the dependency chain for Net_Revenue? | E10: Type your answer here
A11: 3. Are the formulas consistent down each calculated column? | E11: Type your answer here
A12: 4. Is there any row that breaks the calculation pattern? If yes, identify the cell or row without changing it. | E12: Type your answer here
A13: 5. Why would treating a derived field as raw source data be risky during a take-home assessment? | E13: Type your answer here
A16: Line_ID | B16: Order_ID | C16: Product | D16: Region | E16: Units | F16: Unit_Price | G16: Discount | H16: Gross_Revenue | I16: Net_Revenue
A17: L001 | B17: O1001 | C17: Laptop Pro | D17: North | E17: 1 | F17: 1200 | G17: 0 | H17: =E17*F17 | I17: =H17*(1-G17)
A18: L002 | B18: O1001 | C18: Mouse X | D18: North | E18: 2 | F18: 30 | G18: 0.1 | H18: =E18*F18 | I18: =H18*(1-G18)
A19: L003 | B19: O1002 | C19: Laptop Air | D19: West | E19: 1 | F19: 950 | G19: 0.05 | H19: =E19*F19 | I19: =H19*(1-G19)
A20: L004 | B20: O1003 | C20: Mouse X | D20: South | E20: 4 | F20: 30 | G20: 0 | H20: =E20*F20 | I20: 120
A21: L005 | B21: O1004 | C21: Keyboard K | D21: East | E21: 2 | F21: 75 | G21: 0.2 | H21: =E21*F21 | I21: =H21*(1-G21)
A22: L006 | B22: O1005 | C22: Laptop Pro | D22: South | E22: 1 | F22: 1200 | G22: 0.15 | H22: =E22*F22 | I22: =H22*(1-G22)

Sheet 06_DEFINED_NAMES
A1: Exercise 06 — Defined Names
A2: Capability | B2: Use Name Box and Name Manager to discover named cells, ranges, and constants
A3: Difficulty | B3: Intermediate
A5: Scenario | B5: This sheet uses workbook-level Defined Names. Do not infer what they mean only from formulas. Open Formulas → Name Manager and inspect Name, Refers To, and Scope.
A8: Your task
A9: 1. List all Defined Names that are relevant to this sheet. | E9: Type your answer here
A10: 2. For each name, what does it refer to: a cell, a range, or a constant? | E10: Type your answer here
A11: 3. Which name represents the sales data block? | E11: Type your answer here
A12: 4. Which names could affect analysis logic even though they are not columns in the sales table? | E12: Type your answer here
A13: 5. What is the difference between using the Name Box for navigation and Name Manager for discovery? | E13: Type your answer here
A18: Control / assumptions
A19: Tax rate | B19: 0.17 | H19: Example formula using a name
A20: Report date | B20: 46250 | H20: After-tax sales | I20: =SUM(F25:F29)*(1-Tax_Rate)
A21: Target margin | B21: 0.35
A24: Sale_ID | B24: Date | C24: Region | D24: Product | E24: Units | F24: Revenue
A25: S01 | B25: 46204 | C25: North | D25: Laptop Pro | E25: 1 | F25: 1200
A26: S02 | B26: 46204 | C26: South | D26: Mouse X | E26: 3 | F26: 90
A27: S03 | B27: 46205 | C27: West | D27: Laptop Air | E27: 1 | F27: 950
A28: S04 | B28: 46206 | C28: North | D28: Keyboard K | E28: 2 | F28: 150
A29: S05 | B29: 46207 | C29: South | D29: Mouse X | E29: 4 | F29: 120

Sheet 07_FORMULA_LOGIC
A1: Exercise 07 — Formula Logic
A2: Capability | B2: Inspect existing formulas and trace calculation dependencies
A3: Difficulty | B3: Intermediate
A5: Scenario | B5: The sheet contains source data plus a KPI block built by another analyst. Your task is to understand the logic that already exists, not to rewrite it.
A8: Your task
A9: 1. Which source columns feed the Gross Sales KPI? | E9: Type your answer here
A10: 2. Which KPI depends on another KPI rather than directly on source rows? | E10: Type your answer here
A11: 3. For the Margin % KPI, describe the dependency chain from source fields to final output. | E11: Type your answer here
A12: 4. Which Excel auditing feature could help you inspect a selected KPI cell’s precedents? | E12: Type your answer here
A13: 5. If Gross Cost were wrong, which downstream KPI(s) would also be affected? | E13: Type your answer here
A16: Order_ID | B16: Region | C16: Product | D16: Units | E16: Unit_Price | F16: Unit_Cost | G16: Gross_Sales | H16: Gross_Cost
A17: O1 | B17: North | C17: Laptop Pro | D17: 1 | E17: 1200 | F17: 800 | G17: =D17*E17 | H17: =D17*F17
A18: O2 | B18: South | C18: Mouse X | D18: 3 | E18: 30 | F18: 12 | G18: =D18*E18 | H18: =D18*F18 | J18: KPI | K18: Formula / Value
A19: O3 | B19: West | C19: Laptop Air | D19: 1 | E19: 950 | F19: 650 | G19: =D19*E19 | H19: =D19*F19 | J19: Gross Sales | K19: =SUM(G17:G21)
A20: O4 | B20: North | C20: Keyboard K | D20: 2 | E20: 75 | F20: 35 | G20: =D20*E20 | H20: =D20*F20 | J20: Gross Cost | K20: =SUM(H17:H21)
A21: O5 | B21: South | C21: Mouse X | D21: 4 | E21: 30 | F21: 12 | G21: =D21*E21 | H21: =D21*F21 | J21: Gross Profit | K21: =K19-K20
J22: Margin % | K22: =K21/K19

Sheet 08_HIDDEN_DEP
A1: Exercise 08 — Hidden Dependency
A2: Capability | B2: Identify formulas that depend on hidden workbook content
A3: Difficulty | B3: Intermediate
A5: Scenario | B5: A visible pricing sheet converts EUR list prices to USD. The conversion appears in formulas, but the rate is not visible on this sheet. Find where the dependency lives before changing anything.
A8: Your task
A9: 1. Which formula cell(s) depend on another worksheet? | E9: Type your answer here
A10: 2. What worksheet is referenced by the formula? | E10: Type your answer here
A11: 3. Is that worksheet currently visible? How would you inspect it safely? | E11: Type your answer here
A12: 4. What business assumption is stored there? | E12: Type your answer here
A13: 5. Why should you understand the dependency before editing or replacing the formula? | E13: Type your answer here
A16: Product_ID | B16: Product | C16: EUR_List_Price | D16: USD_List_Price
A17: P01 | B17: Laptop Pro | C17: 1050 | D17: =C17*'08_RATES_REF'!$B$2
A18: P02 | B18: Laptop Air | C18: 830 | D18: =C18*'08_RATES_REF'!$B$2
A19: P03 | B19: Mouse X | C19: 26 | D19: =C19*'08_RATES_REF'!$B$2
A20: P04 | B20: Keyboard K | C20: 65 | D20: =C20*'08_RATES_REF'!$B$2

Sheet 08_RATES_REF
A1: Assumption | B1: Value
A2: EUR_to_USD | B2: 1.09
A3: Last_updated | B3: 46235

Sheet 09_PIVOT_READING
A1: Exercise 09 — PivotTable Discovery
A2: Capability | B2: Inspect Pivot logic: source, fields, aggregation, and display logic
A3: Difficulty | B3: Intermediate
A5: Scenario | B5: You inherit a report that contains a PivotTable-style summary. In a real workbook you would click inside the PivotTable and inspect its source, Fields pane, Value Field Settings, and Show Values As. This portable exercise reproduces the source data and output logic without embedding a live Pivot object.
A8: Your task
A9: 1. From the summary, what field is acting as the row dimension? | E9: Type your answer here
A10: 2. What measures are being summarized, and what aggregation is used for each? | E10: Type your answer here
A11: 3. What would you inspect in Excel to confirm the PivotTable source range or Table? | E11: Type your answer here
A12: 4. What setting would you inspect to distinguish Sum of Revenue from Count of Revenue or Average of Revenue? | E12: Type your answer here
A13: 5. If the displayed value were “% of Grand Total” rather than the raw sum, where would you verify that in a real PivotTable? | E13: Type your answer here
A16: Order_ID | B16: Date | C16: Region | D16: Product | E16: Revenue | H16: Region | I16: Revenue | J16: Order Count | K16: % of Total
A17: O1 | B17: 46204 | C17: North | D17: Laptop Pro | E17: 1200 | H17: North | I17: =SUMIF($C$17:$C$22,H17,$E$17:$E$22) | J17: =COUNTIF($C$17:$C$22,H17) | K17: =I17/SUM($I$17:$I$19)
A18: O2 | B18: 46204 | C18: South | D18: Mouse X | E18: 90 | H18: South | I18: =SUMIF($C$17:$C$22,H18,$E$17:$E$22) | J18: =COUNTIF($C$17:$C$22,H18) | K18: =I18/SUM($I$17:$I$19)
A19: O3 | B19: 46205 | C19: West | D19: Laptop Air | E19: 950 | H19: West | I19: =SUMIF($C$17:$C$22,H19,$E$17:$E$22) | J19: =COUNTIF($C$17:$C$22,H19) | K19: =I19/SUM($I$17:$I$19)
A20: O4 | B20: 46205 | C20: North | D20: Keyboard K | E20: 150
A21: O5 | B21: 46206 | C21: South | D21: Mouse X | E21: 120
A22: O6 | B22: 46207 | C22: North | D22: Mouse X | E22: 60 | H22: Important: this is not a live PivotTable object. It is a portable practice snapshot. The goal is to learn what you would verify in a real PivotTable before trusting the displayed numbers.

Sheet 10_EXTERNAL_CLUES
A1: Exercise 10 — External / Connection Clues
A2: Capability | B2: Recognize signs of external dependencies and choose safe inspection steps
A3: Difficulty | B3: Intermediate
A5: Scenario | B5: You open a workbook and find the evidence below. This exercise is about recognizing when you must inspect Workbook Links or Queries & Connections before refreshing or breaking anything. The external sources are intentionally not live so the practice file remains portable.
A8: Your task
A9: 1. Which clue suggests a dependency on another Excel workbook? | E9: Type your answer here
A10: 2. Which clue suggests data may be loaded by a query or connection rather than entered manually? | E10: Type your answer here
A11: 3. What would you inspect in Excel before using Refresh All? | E11: Type your answer here
A12: 4. Why would breaking an external link be a risky first action? | E12: Type your answer here
A13: 5. Which of these clues affect workbook discovery even before you analyze the data values? | E13: Type your answer here
A16: Evidence type | B16: What you see in the workbook | C16: Status
A17: Formula clue | B17: ='[Pricing_Master.xlsx]Rates'!$B$2 | C17: External workbook reference
A18: Query clue | B18: Query name: Sales_Import | Load to: tbl_Sales | C18: Connection metadata
A19: Refresh clue | B19: Last refreshed: 2026-08-01 07:00 | C19: Potentially stale
A20: Output clue | B20: Dashboard formulas reference tbl_Sales | C20: Downstream dependency
A23: This sheet does not contain a live external connection. It trains recognition and safe decision-making; a live Power Query/Pivot workbook should be practiced separately in Excel.

Sheet 11_BUSINESS_TO_DATA
A1: Exercise 11 — Business Question → Data
A2: Capability | B2: Translate questions into fields, grain, joins, and derived metrics
A3: Difficulty | B3: Intermediate
A5: Scenario | B5: You are given three available datasets. Do not solve the business questions. For each one, identify what data is required and whether a join or calculated metric is needed.
A8: Your task
A9: 1. Which category generated the highest revenue in Q2? | E9: Type your answer here
A10: 2. Which customer segment had the highest average order value? | E10: Type your answer here
A11: 3. Which product had the highest unit sales in the North region? | E11: Type your answer here
A12: 4. What was profit by month? | E12: Type your answer here
A13: 5. Which customer had the best performance? Is this question answerable as written? | E13: Type your answer here
A16: Dataset | B16: Available fields
A17: Sales | B17: Order_Line_ID, Order_ID, Date, Customer_ID, Product_ID, Region, Units, Unit_Price
A18: Products | B18: Product_ID, Product, Category, Unit_Cost
A19: Customers | B19: Customer_ID, Customer_Name, Segment

Sheet 12_AMBIGUITY
A1: Exercise 12 — Missing Information & Ambiguity
A2: Capability | B2: Detect requests that cannot be answered safely without a definition or missing data
A3: Difficulty | B3: Intermediate
A5: Scenario | B5: A take-home assignment contains vague questions. Strong analysis includes recognizing when the problem definition is incomplete instead of silently choosing an arbitrary interpretation.
A8: Your task
A9: 1. “Which customer is best?” — What definition is missing? | E9: Type your answer here
A10: 2. “Calculate profit by product.” You have Revenue but no Cost field. What is missing? | E10: Type your answer here
A11: 3. “Show monthly growth.” The dataset contains only July data. Can the request be answered? | E11: Type your answer here
A12: 4. “Find the top region.” What measure must be defined before ranking regions? | E12: Type your answer here
A13: 5. “Calculate average order value.” Sales is at order-line grain. What grain/denominator issue must be resolved first? | E13: Type your answer here
A16: Your goal is not to invent assumptions. State exactly what is ambiguous or unavailable and what definition/data would resolve it.

Sheet 13_DATA_QUALITY
A1: Exercise 13 — Data Quality Quick Scan
A2: Capability | B2: Detect data-quality risks before analysis
A3: Difficulty | B3: Foundation → Intermediate
A5: Scenario | B5: You receive a transaction extract that looks usable at first glance. Do not clean it and do not calculate results. Inspect the values, types, blanks, labels, and identifier behavior first.
A8: Your task
A9: 1. What does one row represent, and what is the intended row-level identifier? | E9: Type your answer here
A10: 2. Is the intended identifier actually unique? What evidence do you see? | E10: Type your answer here
A11: 3. Which fields contain missing values that could affect analysis? | E11: Type your answer here
A12: 4. Which fields contain inconsistent underlying data types? | E12: Type your answer here
A13: 5. Which label inconsistency could split one logical category into multiple groups? | E13: Type your answer here
A14: 6. Which issues would you resolve or document before analyzing revenue? | E14: Type your answer here
A17: Transaction_ID | B17: Date | C17: Customer_ID | D17: Product_ID | E17: Category | F17: Region | G17: Units | H17: Unit_Price
A18: T001 | B18: 46204 | C18: C101 | D18: P01 | E18: Computers | F18: North | G18: 1 | H18: 1200
A19: T002 | B19: 46204 | C19: C102 | D19: P03 | E19: Accessories | F19: South | G19: 3 | H19: 30
A20: T003 | B20: 46205 | C20: C103 | D20: P02 | E20: Computers | F20: West | G20: 1 | H20: 950
A21: T003 | B21: 46205 | C21: C104 | D21: P04 | E21: Accessories | F21: East | G21: 2 | H21: 75
A22: T005 | B22: 46206 | C22: C105 | D22: P03 | E22: Accessories | F22: South | G22: 4 | H22: 30
A23: T006 | B23: 2026-07-04 | C23: C106 | D23: P01 | E23: Computers | G23: 1 | H23: 1200
A24: T007 | B24: 46207 | D24: P03 | E24: accessories | F24: North | G24: 2 | H24: 30
A25: T008 | B25: 46208 | C25: C108 | D25: P04 | E25: Accessories | F25: North | G25: 1 | H25: 75

Sheet 14_KEY_INTEGRITY
A1: Exercise 14 — Key Integrity
A2: Capability | B2: Validate keys before lookups or joins
A3: Difficulty | B3: Intermediate
A5: Scenario | B5: You have Sales plus Product and Customer reference tables. Do not perform a lookup yet. First verify that the intended keys are unique where expected and that Sales contains valid foreign keys.
A8: Your task
A9: 1. Which fields should connect Sales to Products and Sales to Customers? | E9: Type your answer here
A10: 2. On which side of each relationship should the key be unique? | E10: Type your answer here
A11: 3. Do the reference tables actually satisfy that uniqueness requirement? Identify any duplicate keys. | E11: Type your answer here
A12: 4. Does every nonblank foreign key in Sales have a matching reference row? Identify exceptions. | E12: Type your answer here
A13: 5. Are any required join keys blank in Sales? Where? | E13: Type your answer here
A14: 6. What could go wrong if you perform lookups/joins before resolving these key issues? | E14: Type your answer here
A17: Line_ID | B17: Order_ID | C17: Customer_ID | D17: Product_ID | E17: Date | F17: Units | G17: Revenue | I17: Product_ID | J17: Product | K17: Category | L17: Standard_Price | N17: Customer_ID | O17: Customer_Name | P17: Segment
A18: L001 | B18: O1001 | C18: C101 | D18: P01 | E18: 46204 | F18: 1 | G18: 1200 | I18: P01 | J18: Laptop Pro | K18: Computers | L18: 1200 | N18: C101 | O18: Orion Labs | P18: SMB
A19: L002 | B19: O1001 | C19: C101 | D19: P03 | E19: 46204 | F19: 2 | G19: 60 | I19: P02 | J19: Laptop Air | K19: Computers | L19: 950 | N19: C102 | O19: Nova Retail | P19: Enterprise
A20: L003 | B20: O1002 | C20: C102 | D20: P02 | E20: 46205 | F20: 1 | G20: 950 | I20: P03 | J20: Mouse X | K20: Accessories | L20: 30 | N20: C103 | O20: Blue Peak | P20: SMB
A21: L004 | B21: O1003 | C21: C103 | D21: P03 | E21: 46205 | F21: 4 | G21: 120 | I21: P03 | J21: Mouse X - Alternate | K21: Accessories | L21: 35 | N21: C103 | O21: Blue Peak Holdings | P21: Enterprise
A22: L005 | B22: O1004 | C22: C999 | D22: P99 | E22: 46206 | F22: 1 | G22: 75 | I22: P04 | J22: Keyboard K | K22: Accessories | L22: 75 | N22: C104 | O22: Vertex Works | P22: SMB
A23: L006 | B23: O1005 | C23: C104 | E23: 46207 | F23: 2 | G23: 150

Sheet 15_FILTERS_HIDDEN
A1: Exercise 15 — Filters, Hidden Rows & Hidden Columns
A2: Capability | B2: Detect workbook visibility state before trusting what is on screen
A3: Difficulty | B3: Intermediate
A5: Scenario | B5: The source extract is on the right side of this sheet. Before counting or totaling anything, inspect filters, row visibility, column visibility, and whether the visible records represent the complete dataset.
A8: Your task
A9: 1. Is an AutoFilter active on the source extract? Which field and criterion are involved? | E9: Type your answer here
A10: 2. How many data rows exist in the extract, and how many are currently visible? | E10: Type your answer here
A11: 3. Is any source column hidden? Which field is it? | E11: Type your answer here
A12: 4. Besides filtered rows, is any additional source row hidden/collapsed? | E12: Type your answer here
A13: 5. Why could analyzing only the visible cells produce a misleading answer? | E13: Type your answer here
A14: 6. What visibility checks should you complete before trusting counts or totals? | E14: Type your answer here
J17: Line_ID | K17: Date | L17: Customer_ID | M17: Product_ID | N17: Region | O17: Status | P17: Units | Q17: Revenue
J18: L001 | K18: 46204 | L18: C101 | M18: P01 | N18: North | O18: Active | P18: 1 | Q18: 1200
J19: L002 | K19: 46204 | L19: C102 | M19: P03 | N19: South | O19: Active | P19: 2 | Q19: 60
J20: L003 | K20: 46205 | L20: C103 | M20: P02 | N20: West | O20: Cancelled | P20: 1 | Q20: 950
J21: L004 | K21: 46205 | L21: C104 | M21: P03 | N21: North | O21: Active | P21: 4 | Q21: 120
J22: L005 | K22: 46206 | L22: C105 | M22: P04 | N22: East | O22: Active | P22: 1 | Q22: 75
J23: L006 | K23: 46206 | L23: C106 | M23: P01 | N23: South | O23: Cancelled | P23: 1 | Q23: 1200
J24: L007 | K24: 46207 | L24: C107 | M24: P04 | N24: North | O24: Active | P24: 2 | Q24: 150

Sheet 16_DATA_TYPES
A1: Exercise 16 — Data Types vs Display Format
A2: Capability | B2: Distinguish underlying values from how Excel displays them
A3: Difficulty | B3: Intermediate
A5: Scenario | B5: Several cells look similar on screen but are stored differently. Do not normalize them yet. Inspect the underlying values and formats so you can predict how sorting, filtering, formulas, and joins may behave.
A8: Your task
A9: 1. Which Date_Value cells are true Excel dates/numbers, and which are text? | E9: Type your answer here
A10: 2. Which Revenue_Value cells are numeric and which are numbers stored as text? | E10: Type your answer here
A11: 3. Which Discount values only look like percentages because of text or cell formatting? | E11: Type your answer here
A12: 4. Which identifier/code could lose leading zeros if its underlying type changes? | E12: Type your answer here
A13: 5. Which Units or Flag values are stored inconsistently across rows? | E13: Type your answer here
A14: 6. What analysis risks do these type inconsistencies create? | E14: Type your answer here
A17: Record_ID | B17: Date_Value | C17: Revenue_Value | D17: Discount | E17: Product_Code | F17: Units | G17: Flag | H17: Notes
A18: 00125 | B18: 46204 | C18: 1200 | D18: 0.15 | E18: 0007 | F18: 2 | G18: TRUE | H18: Consistent row
A19: 00126 | B19: 2026-07-02 | C19: 950 | D19: 15% | E19: 0008 | F19: 3 | G19: TRUE | H19: Values stored as text
A20: 00127 | B20: 46206 | C20: $1,200 | D20: 0.1 | E20: 9 | F20: 1 | G20: FALSE | H20: Code only looks padded
A21: 128 | B21: 46207 | C21: 75 | D21: 0.05 | E21: 0010 | F21: 4 | G21: TRUE | H21: ID only looks padded
A22: 00129 | B22: 46205 | C22: 30 | D22: 0.2 | E22: 0011 | F22: 2 | G22: TRUE | H22: Date serial not formatted

Sheet 17_WORKBOOK_HEALTH
A1: Exercise 17 — Workbook Health & Calculation Clues
A2: Capability | B2: Assess whether existing outputs are trustworthy before editing
A3: Difficulty | B3: Intermediate → Challenge
A5: Scenario | B5: You inherit a small source table and a KPI block from another analyst. Some clues suggest incomplete ranges, stale state, and a previously broken dependency. Do not fix anything yet—diagnose what deserves review.
A8: Your task
A9: 1. Which KPI formula appears to have incomplete source coverage? | E9: Type your answer here
A10: 2. Which KPI values are formulas, and which are static/hardcoded evidence? | E10: Type your answer here
A11: 3. Which recency clue should make you question whether the workbook is up to date? | E11: Type your answer here
A12: 4. Which Excel calculation setting should you verify before trusting displayed formula results? | E12: Type your answer here
A13: 5. Which recorded formula clue indicates a broken-reference risk in the inherited model? | E13: Type your answer here
A14: 6. In what order would you validate workbook health before changing formulas? | E14: Type your answer here
A17: Date | B17: Order_ID | C17: Revenue | D17: Status | F17: KPI / Clue | G17: Value | H17: Evidence
A18: 46204 | B18: O1001 | C18: 1200 | D18: OK | F18: Total Revenue | G18: =SUM(C18:C21) | H18: Formula stops before the final source row
A19: 46204 | B19: O1002 | C19: 60 | D19: OK | F19: Order Lines | G19: =COUNTA(B18:B22) | H19: Formula
A20: 46205 | B20: O1003 | C20: 950 | D20: Review | F20: Review Rate | G20: =COUNTIF(D18:D22,"Review")/COUNTA(D18:D22) | H20: Formula
A21: 46205 | B21: O1004 | C21: 120 | D21: OK | F21: Last Refresh | G21: 46203 | H21: Static timestamp
A22: 46206 | B22: O1005 | C22: 75 | D22: Review | F22: Calculation Mode | G22: Manual | H22: Recorded in handoff note — verify in Excel
F23: Broken formula clue | G23: Formula: =SUM(#REF!) | H23: Portable evidence from prior version; not a live error

Sheet 18_VALIDATION
A1: Exercise 18 — Validation & Reconciliation
A2: Capability | B2: Prove that an output is trustworthy before presenting it
A3: Difficulty | B3: Challenge
A5: Scenario | B5: A report already contains a transaction table, a category summary, and a KPI block. Do not redesign it. Your task is to decide which outputs should reconcile and whether the existing logic is robust enough to trust.
A8: Your task
A9: 1. Which revenue totals should reconcile to each other across the source, category summary, and KPI block? | E9: Type your answer here
A10: 2. Does the Reported Revenue formula cover every source row? What would you inspect? | E10: Type your answer here
A11: 3. How can category subtotals serve as an independent cross-check of total revenue? | E11: Type your answer here
A12: 4. At order-line grain, how would you validate the distinct order count rather than trusting a hardcoded KPI? | E12: Type your answer here
A13: 5. If a new source row is appended, which formulas/ranges are most at risk of not expanding? | E13: Type your answer here
A14: 6. Write a concise pre-delivery validation checklist for this report. | E14: Type your answer here
A17: Line_ID | B17: Order_ID | C17: Category | D17: Region | E17: Units | F17: Unit_Price | G17: Revenue | J17: Category | K17: Revenue | M17: KPI | N17: Value
A18: L001 | B18: O1001 | C18: Computers | D18: North | E18: 1 | F18: 1200 | G18: =E18*F18 | J18: Computers | K18: =SUMIF($C$18:$C$24,J18,$G$18:$G$24) | M18: Reported Revenue | N18: =SUM(G18:G23)
A19: L002 | B19: O1001 | C19: Accessories | D19: North | E19: 2 | F19: 30 | G19: =E19*F19 | J19: Accessories | K19: =SUMIF($C$18:$C$24,J19,$G$18:$G$24) | M19: Order Lines | N19: =COUNTA(A18:A24)
A20: L003 | B20: O1002 | C20: Computers | D20: West | E20: 1 | F20: 950 | G20: =E20*F20 | J20: Total | K20: =SUM(K18:K19) | M20: Distinct Orders | N20: 6
A21: L004 | B21: O1003 | C21: Accessories | D21: South | E21: 4 | F21: 30 | G21: =E21*F21 | M21: Source Rows | N21: =ROWS(A18:A24)
A22: L005 | B22: O1004 | C22: Accessories | D22: East | E22: 2 | F22: 75 | G22: =E22*F22
A23: L006 | B23: O1005 | C23: Computers | D23: South | E23: 1 | F23: 1200 | G23: =E23*F23
A24: L007 | B24: O1006 | C24: Accessories | D24: North | E24: 1 | F24: 75 | G24: =E24*F24

Sheet 19_FULL_DISCOVERY
A1: Exercise 19 — Full Discovery Challenge
A2: Capability | B2: Build and validate a mental map of an unfamiliar workbook case
A3: Difficulty | B3: Challenge
A5: Scenario | B5: You inherited this workbook section from another analyst. It contains source-like data, reference data, formulas, a Defined Name, a hidden assumption, hidden worksheet state, and several data-quality/key risks. Do not fix anything. Build and validate a discovery map first.
A8: Your task
A9: 1. What is the grain of the Sales table, and what is its row-level identifier? | E9: Type your answer here
A10: 2. Which fields are source inputs and which are derived calculations? | E10: Type your answer here
A11: 3. What key connects Sales to Products, and does the reference side satisfy uniqueness? Are any Sales keys unmatched? | E11: Type your answer here
A12: 4. Perform a quick quality scan. Which blanks, type inconsistencies, or label inconsistencies could affect analysis? | E12: Type your answer here
A13: 5. Are any source rows or columns hidden, and is there evidence of an active filter? | E13: Type your answer here
A14: 6. Find the Defined Name beginning with FD_. What does it refer to? | E14: Type your answer here
A15: 7. Which formula depends on a hidden worksheet, and what assumption is stored there? | E15: Type your answer here
A16: 8. For “Which category had the highest net revenue?”, what fields, relationships, calculations, and blockers must be considered? | E16: Type your answer here
A17: 9. Before trusting the KPI block, which totals/counts would you reconcile back to source? | E17: Type your answer here
A18: 10. Write a 6-line mental map: source objects, grain, keys, derived logic, dependencies, and quality/visibility risks. | E18: Type your answer here
P20: KPI | Q20: Value | R20: Comment
A21: Line_ID | B21: Order_ID | C21: Date | D21: Customer_ID | E21: Product_ID | F21: Region | G21: Units | H21: Unit_Price | I21: Net_Revenue | J21: Source_System | K21: Product_ID | L21: Product | M21: Category | N21: Unit_Cost | P21: Net Revenue | Q21: =SUM(I22:I27) | R21: Derived output
A22: FL001 | B22: FO1001 | C22: 46204 | D22: C101 | E22: P01 | F22: North | G22: 1 | H22: 1200 | I22: =G22*H22*(1-'19_FD_ASSUMPTIONS'!$B$2) | J22: CRM | K22: P01 | L22: Laptop Pro | M22: Computers | N22: 800 | P22: Order Lines | Q22: =COUNTA(A22:A27) | R22: Derived output
A23: FL002 | B23: FO1001 | C23: 46204 | D23: C101 | E23: P03 | F23: North | G23: 2 | H23: 30 | I23: =G23*H23*(1-'19_FD_ASSUMPTIONS'!$B$2) | J23: WEB | K23: P02 | L23: Laptop Air | M23: Computers | N23: 650 | P23: Review Target | Q23: =FD_Review_Target | R23: Named dependency
A24: FL003 | B24: FO1002 | C24: 46205 | D24: C102 | E24: P02 | F24: West | G24: 1 | H24: 950 | I24: =G24*H24*(1-'19_FD_ASSUMPTIONS'!$B$2) | J24: CRM | K24: P03 | L24: Mouse X | M24: Accessories | N24: 12
A25: FL004 | B25: FO1003 | C25: 46205 | D25: C103 | E25: P03 | F25: South | G25: 4 | H25: 30 | I25: =G25*H25*(1-'19_FD_ASSUMPTIONS'!$B$2) | J25: WEB | K25: P04 | L25: Keyboard K | M25: Accessories | N25: 35
A26: FL005 | B26: FO1004 | C26: 46206 | E26: P04 | F26: East | G26: 2 | H26: 75 | I26: =G26*H26*(1-'19_FD_ASSUMPTIONS'!$B$2) | J26: CRM | K26: P03 | L26: Mouse X - Alternate | M26: Accessories | N26: 14 | P26: Control value | Q26: 0.9
A27: FL006 | B27: FO1005 | C27: 46207 | D27: C105 | E27: P99 | F27: South | G27: 1 | H27: 1200 | I27: =G27*H27*(1-'19_FD_ASSUMPTIONS'!$B$2) | J27: PARTNER

Sheet 19_FD_ASSUMPTIONS
A1: Assumption | B1: Value
A2: Standard_Discount | B2: 0.05
A3: Owner | B3: Finance Ops
